{
  "generated": "2026-05-30T23:34:22.091291Z",
  "item_count": 25,
  "cutoff_days": 35,
  "items": [
    {
      "title": "New City/County Government Center",
      "link": "https://forum.urbanplanet.org/topic/121257-new-citycounty-government-center/",
      "published": null,
      "description": "",
      "source": "Urban Planet Spartanburg"
    },
    {
      "title": "Greenways in Sparkle City",
      "link": "https://forum.urbanplanet.org/topic/116698-greenways-in-sparkle-city/",
      "published": null,
      "description": "",
      "source": "Urban Planet Spartanburg"
    },
    {
      "title": "Sparkle City Eateries",
      "link": "https://forum.urbanplanet.org/topic/21039-sparkle-city-eateries/",
      "published": null,
      "description": "",
      "source": "Urban Planet Spartanburg"
    },
    {
      "title": "The Grain District",
      "link": "https://forum.urbanplanet.org/topic/51116-the-grain-district/",
      "published": null,
      "description": "",
      "source": "Urban Planet Spartanburg"
    },
    {
      "title": "245 W. Main St - 7-story Grain District Office Building",
      "link": "https://forum.urbanplanet.org/topic/130829-245-w-main-st-7-story-grain-district-office-building/",
      "published": null,
      "description": "",
      "source": "Urban Planet Spartanburg"
    },
    {
      "title": "Downtown Fairfield Inn",
      "link": "https://forum.urbanplanet.org/topic/120599-downtown-fairfield-inn/",
      "published": null,
      "description": "",
      "source": "Urban Planet Spartanburg"
    },
    {
      "title": "Beaumont Mill",
      "link": "https://forum.urbanplanet.org/topic/117612-beaumont-mill/",
      "published": null,
      "description": "",
      "source": "Urban Planet Spartanburg"
    },
    {
      "title": "Spartanburg Photo of the Day",
      "link": "https://forum.urbanplanet.org/topic/33908-spartanburg-photo-of-the-day/",
      "published": null,
      "description": "",
      "source": "Urban Planet Spartanburg"
    },
    {
      "title": "Downtown Projects & Developments",
      "link": "https://forum.urbanplanet.org/topic/33746-downtown-projects-developments/",
      "published": null,
      "description": "",
      "source": "Urban Planet Spartanburg"
    },
    {
      "title": "Spartanburg Off-Topic",
      "link": "https://forum.urbanplanet.org/topic/16080-spartanburg-off-topic/",
      "published": null,
      "description": "",
      "source": "Urban Planet Spartanburg"
    },
    {
      "title": "Transportation, Infrastructure, and Traffic",
      "link": "https://forum.urbanplanet.org/topic/120790-transportation-infrastructure-and-traffic/",
      "published": null,
      "description": "",
      "source": "Urban Planet Spartanburg"
    },
    {
      "title": "Mary Black Rail Trail",
      "link": "https://forum.urbanplanet.org/topic/51935-mary-black-rail-trail/",
      "published": null,
      "description": "",
      "source": "Urban Planet Spartanburg"
    },
    {
      "title": "Herald-Journal Site Developments",
      "link": "https://forum.urbanplanet.org/topic/130771-herald-journal-site-developments/",
      "published": null,
      "description": "",
      "source": "Urban Planet Spartanburg"
    },
    {
      "title": "Northside Developments",
      "link": "https://forum.urbanplanet.org/topic/53313-northside-developments/",
      "published": null,
      "description": "",
      "source": "Urban Planet Spartanburg"
    },
    {
      "title": "First Baptist Additions & Renovations",
      "link": "https://forum.urbanplanet.org/topic/120916-first-baptist-additions-renovations/",
      "published": null,
      "description": "",
      "source": "Urban Planet Spartanburg"
    },
    {
      "title": "Kennedy & Converse Apartments",
      "link": "https://forum.urbanplanet.org/topic/121150-kennedy-converse-apartments/",
      "published": null,
      "description": "",
      "source": "Urban Planet Spartanburg"
    },
    {
      "title": "Eastside Developments",
      "link": "https://forum.urbanplanet.org/topic/120895-eastside-developments/",
      "published": null,
      "description": "",
      "source": "Urban Planet Spartanburg"
    },
    {
      "title": "Drayton Mill Renovation",
      "link": "https://forum.urbanplanet.org/topic/115905-drayton-mill-renovation/",
      "published": null,
      "description": "",
      "source": "Urban Planet Spartanburg"
    },
    {
      "title": "Spartanburg Area Economic Developments",
      "link": "https://forum.urbanplanet.org/topic/41817-spartanburg-area-economic-developments/",
      "published": null,
      "description": "",
      "source": "Urban Planet Spartanburg"
    },
    {
      "title": "Saluda Grade Trail",
      "link": "https://forum.urbanplanet.org/topic/121499-saluda-grade-trail/",
      "published": null,
      "description": "",
      "source": "Urban Planet Spartanburg"
    },
    {
      "title": "What will become of the Coca-Cola building?",
      "link": "https://forum.urbanplanet.org/topic/118322-what-will-become-of-the-coca-cola-building/",
      "published": null,
      "description": "",
      "source": "Urban Planet Spartanburg"
    },
    {
      "title": "Historic Intown Neighborhoods",
      "link": "https://forum.urbanplanet.org/topic/25387-historic-intown-neighborhoods/",
      "published": null,
      "description": "",
      "source": "Urban Planet Spartanburg"
    },
    {
      "title": "Greater Spartanburg Projects & Developments",
      "link": "https://forum.urbanplanet.org/topic/8516-greater-spartanburg-projects-developments/",
      "published": null,
      "description": "",
      "source": "Urban Planet Spartanburg"
    },
    {
      "title": "Fifth Third Park | $425 million MiLB Stadium + Mixed-Use Development",
      "link": "https://forum.urbanplanet.org/topic/130602-fifth-third-park-425-million-milb-stadium-mixed-use-development/",
      "published": null,
      "description": "",
      "source": "Urban Planet Spartanburg"
    },
    {
      "title": "The Montgomery Building",
      "link": "https://forum.urbanplanet.org/topic/41839-the-montgomery-building/",
      "published": null,
      "description": "",
      "source": "Urban Planet Spartanburg"
    }
  ]
}